{"keys": ["60678", "60766", "60767", "60768", "60769", "60770", "60771", "60772", "", "60576", "60577", "60578", "60579", "60580", "60581", "60582", "60569", "60570", "60571", "60572", "60563", "60564", "60565"], "data": {"60569": {"kc": 30, "oid_1": 60569, "rfor": 13.5, "run": 0, "rcoa": 7.6, "rorc": 0, "rtree": 0, "rara": 5.3, "valid": 1, "rabd": 0.5, "rwat": 0, "rtra": 0, "sc": 407, "rpad": 0.9, "cl6": 16, "rbuil": 7.9, "rsea": 64.4, "m3cd": 50351583, "cl3": 1}, "60563": {"kc": 30, "oid_1": 60563, "rfor": -99, "run": -99, "rcoa": -99, "rorc": -99, "rtree": -99, "rara": -99, "valid": 0, "rabd": -99, "rwat": -99, "rtra": -99, "sc": 407, "rpad": -99, "cl6": -99, "rbuil": -99, "rsea": -99, "m3cd": 50351573, "cl3": -99}, "60564": {"kc": 30, "oid_1": 60564, "rfor": 0, "run": 0, "rcoa": 4.5, "rorc": 0, "rtree": 0, "rara": 0, "valid": 1, "rabd": 0, "rwat": 0, "rtra": 0, "sc": 407, "rpad": 0, "cl6": 16, "rbuil": 0, "rsea": 95.5, "m3cd": 50351575, "cl3": 1}, "60565": {"kc": 30, "oid_1": 60565, "rfor": -99, "run": -99, "rcoa": -99, "rorc": -99, "rtree": -99, "rara": -99, "valid": 0, "rabd": -99, "rwat": -99, "rtra": -99, "sc": 407, "rpad": -99, "cl6": -99, "rbuil": -99, "rsea": -99, "m3cd": 50351576, "cl3": -99}, "60768": {"kc": 30, "oid_1": 60768, "rfor": 80.9, "run": 0, "rcoa": 0.2, "rorc": 0, "rtree": 0, "rara": 2.6, "valid": 1, "rabd": 0, "rwat": 4.1, "rtra": 0, "sc": 407, "rpad": 5.9, "cl6": 35, "rbuil": 6.5, "rsea": 0, "m3cd": 50352502, "cl3": 3}, "60769": {"kc": 30, "oid_1": 60769, "rfor": 98.7, "run": 0, "rcoa": 0, "rorc": 0, "rtree": 0, "rara": 0, "valid": 1, "rabd": 0, "rwat": 0.7, "rtra": 0, "sc": 407, "rpad": 0.7, "cl6": 35, "rbuil": 0, "rsea": 0, "m3cd": 50352503, "cl3": 3}, "60582": {"kc": 30, "oid_1": 60582, "rfor": 84.7, "run": 0, "rcoa": 0, "rorc": 0, "rtree": 0, "rara": 0, "valid": 1, "rabd": 13, "rwat": 0.4, "rtra": 0, "sc": 407, "rpad": 0.4, "cl6": 38, "rbuil": 1.6, "rsea": 0, "m3cd": 50351596, "cl3": 3}, "60580": {"kc": 30, "oid_1": 60580, "rfor": 98.3, "run": 0, "rcoa": 0, "rorc": 0, "rtree": 0, "rara": 0, "valid": 1, "rabd": 0.1, "rwat": 0, "rtra": 0, "sc": 407, "rpad": 1.3, "cl6": 38, "rbuil": 0.3, "rsea": 0, "m3cd": 50351594, "cl3": 3}, "60581": {"kc": 30, "oid_1": 60581, "rfor": 89.4, "run": 0, "rcoa": 0, "rorc": 0, "rtree": 0, "rara": 0, "valid": 1, "rabd": 6.8, "rwat": 0, "rtra": 0, "sc": 407, "rpad": 3.3, "cl6": 38, "rbuil": 0.5, "rsea": 0, "m3cd": 50351595, "cl3": 3}, "60766": {"kc": 30, "oid_1": 60766, "rfor": 40.1, "run": 0, "rcoa": 5.7, "rorc": 0, "rtree": 0, "rara": 6.5, "valid": 1, "rabd": 3.6, "rwat": 0, "rtra": 0, "sc": 406, "rpad": 6.5, "cl6": 74, "rbuil": 9.2, "rsea": 28.4, "m3cd": 50352500, "cl3": 7}, "60767": {"kc": 30, "oid_1": 60767, "rfor": 76.8, "run": 1.1, "rcoa": 3.3, "rorc": 0, "rtree": 0, "rara": 6.8, "valid": 1, "rabd": 1.3, "rwat": 0, "rtra": 0, "sc": 407, "rpad": 0.1, "cl6": 38, "rbuil": 1.1, "rsea": 9.4, "m3cd": 50352501, "cl3": 3}, "60579": {"kc": 30, "oid_1": 60579, "rfor": 83.4, "run": 2.5, "rcoa": 1, "rorc": 0, "rtree": 0, "rara": 4.6, "valid": 1, "rabd": 2.4, "rwat": 0, "rtra": 0, "sc": 407, "rpad": 0.7, "cl6": 38, "rbuil": 4.3, "rsea": 1.1, "m3cd": 50351593, "cl3": 3}, "60578": {"kc": 30, "oid_1": 60578, "rfor": 17, "run": 1.6, "rcoa": 7.7, "rorc": 0, "rtree": 0, "rara": 6.9, "valid": 1, "rabd": 0, "rwat": 0.5, "rtra": 0, "sc": 407, "rpad": 0, "cl6": 16, "rbuil": 16.1, "rsea": 50.1, "m3cd": 50351592, "cl3": 1}, "60577": {"kc": 30, "oid_1": 60577, "rfor": -99, "run": -99, "rcoa": -99, "rorc": -99, "rtree": -99, "rara": -99, "valid": 0, "rabd": -99, "rwat": -99, "rtra": -99, "sc": 407, "rpad": -99, "cl6": -99, "rbuil": -99, "rsea": -99, "m3cd": 50351591, "cl3": -99}, "60576": {"kc": 30, "oid_1": 60576, "rfor": -99, "run": -99, "rcoa": -99, "rorc": -99, "rtree": -99, "rara": -99, "valid": 0, "rabd": -99, "rwat": -99, "rtra": -99, "sc": 406, "rpad": -99, "cl6": -99, "rbuil": -99, "rsea": -99, "m3cd": 50351590, "cl3": -99}, "60572": {"kc": 30, "oid_1": 60572, "rfor": 45.8, "run": 0.7, "rcoa": 6.4, "rorc": 0, "rtree": 0, "rara": 1.4, "valid": 1, "rabd": 7.1, "rwat": 0, "rtra": 0, "sc": 407, "rpad": 1.4, "cl6": 38, "rbuil": 4.4, "rsea": 32.8, "m3cd": 50351586, "cl3": 3}, "60571": {"kc": 30, "oid_1": 60571, "rfor": 64.9, "run": 0, "rcoa": 3.6, "rorc": 0, "rtree": 0, "rara": 2.2, "valid": 1, "rabd": 5.7, "rwat": 0, "rtra": 0, "sc": 407, "rpad": 0.8, "cl6": 74, "rbuil": 3.7, "rsea": 19.1, "m3cd": 50351585, "cl3": 7}, "60570": {"kc": 30, "oid_1": 60570, "rfor": 41.7, "run": 0.3, "rcoa": 4.3, "rorc": 0, "rtree": 0, "rara": 6.9, "valid": 1, "rabd": 3, "rwat": 0, "rtra": 0, "sc": 407, "rpad": 0.9, "cl6": 38, "rbuil": 9.6, "rsea": 33.3, "m3cd": 50351584, "cl3": 3}, "60678": {"kc": 30, "oid_1": 60678, "rfor": 53, "run": 0, "rcoa": 3.2, "rorc": 0, "rtree": 0, "rara": 8.7, "valid": 1, "rabd": 5, "rwat": 0, "rtra": 1.2, "sc": 406, "rpad": 0.1, "cl6": 38, "rbuil": 1.4, "rsea": 27.5, "m3cd": 50352409, "cl3": 3}, "60771": {"kc": 30, "oid_1": 60771, "rfor": 97.7, "run": 0, "rcoa": 0.8, "rorc": 0, "rtree": 0, "rara": 0, "valid": 1, "rabd": 1, "rwat": 0, "rtra": 0, "sc": 407, "rpad": 0.4, "cl6": 35, "rbuil": 0.1, "rsea": 0, "m3cd": 50352505, "cl3": 3}, "60770": {"kc": 30, "oid_1": 60770, "rfor": 95.7, "run": 0, "rcoa": 0, "rorc": 0, "rtree": 0, "rara": 0.3, "valid": 1, "rabd": 0.8, "rwat": 0, "rtra": 0, "sc": 407, "rpad": 2.9, "cl6": 35, "rbuil": 0.3, "rsea": 0, "m3cd": 50352504, "cl3": 3}, "60772": {"kc": 30, "oid_1": 60772, "rfor": 100, "run": 0, "rcoa": 0, "rorc": 0, "rtree": 0, "rara": 0, "valid": 1, "rabd": 0, "rwat": 0, "rtra": 0, "sc": 407, "rpad": 0, "cl6": 35, "rbuil": 0, "rsea": 0, "m3cd": 50352506, "cl3": 3}}, "grid": ["       !!!!!!!!!##########$$$$$$$$$%%%%%%%%%&&&&&&&&&'''''''''((", "       !!!!!!!!!##########$$$$$$$$$%%%%%%%%%&&&&&&&&&'''''''''((", "       !!!!!!!!!##########$$$$$$$$$%%%%%%%%%&&&&&&&&&'''''''''((", "       !!!!!!!!!##########$$$$$$$$$%%%%%%%%%&&&&&&&&&'''''''''((", "       !!!!!!!!!##########$$$$$$$$$%%%%%%%%%&&&&&&&&&'''''''''((", ")))))))*********++++++++++,,,,,,,,,---------........./////////00", ")))))))*********++++++++++,,,,,,,,,---------........./////////00", ")))))))*********++++++++++,,,,,,,,,---------........./////////00", ")))))))*********++++++++++,,,,,,,,,---------........./////////00", ")))))))*********++++++++++,,,,,,,,,---------........./////////00", ")))))))*********++++++++++,,,,,,,,,---------........./////////00", ")))))))*********++++++++++,,,,,,,,,---------........./////////00", ")))))))))))))))))))))))))))))))))))11111111122222222233333333344", ")))))))))))))))))))))))))))))))))))11111111122222222233333333344", ")))))))))))))))))))))))))))))))))))11111111122222222233333333344", ")))))))))))))))))))))))))))))))))))11111111122222222233333333344", ")))))))))))))))))))))))))))))))))))11111111122222222233333333344", ")))))))))))))))))))))))))))))))))))11111111122222222233333333344", ")))))))))))))))))))))))))))))))))))11111111122222222233333333344", ")))))))))))))))))))))))))))))))))))555555555)))))))))66666666677", ")))))))))))))))))))))))))))))))))))555555555)))))))))66666666677", ")))))))))))))))))))))))))))))))))))555555555)))))))))66666666677", ")))))))))))))))))))))))))))))))))))555555555)))))))))66666666677", ")))))))))))))))))))))))))))))))))))555555555)))))))))66666666677", ")))))))))))))))))))))))))))))))))))555555555)))))))))66666666677", ")))))))))))))))))))))))))))))))))))555555555)))))))))66666666677", ")))))))))))))))))))))))))))))))))))555555555)))))))))66666666677", "))))))))))))))))))))))))))))))))))))))))))))))))))))))))))))))))", "))))))))))))))))))))))))))))))))))))))))))))))))))))))))))))))))", "))))))))))))))))))))))))))))))))))))))))))))))))))))))))))))))))", "))))))))))))))))))))))))))))))))))))))))))))))))))))))))))))))))", "))))))))))))))))))))))))))))))))))))))))))))))))))))))))))))))))", "))))))))))))))))))))))))))))))))))))))))))))))))))))))))))))))))", "))))))))))))))))))))))))))))))))))))))))))))))))))))))))))))))))", "))))))))))))))))))))))))))))))))))))))))))))))))))))))))))))))))", "))))))))))))))))))))))))))))))))))))))))))))))))))))))))))))))))", "))))))))))))))))))))))))))))))))))))))))))))))))))))))))))))))))", "))))))))))))))))))))))))))))))))))))))))))))))))))))))))))))))))", "))))))))))))))))))))))))))))))))))))))))))))))))))))))))))))))))", "))))))))))))))))))))))))))))))))))))))))))))))))))))))))))))))))", "))))))))))))))))))))))))))))))))))))))))))))))))))))))))))))))))", "))))))))))))))))))))))))))))))))))))))))))))))))))))))))))))))))", "))))))))))))))))))))))))))))))))))))))))))))))))))))))))))))))))", "))))))))))))))))))))))))))))))))))))))))))))))))))))))))))))))))", "))))))))))))))))))))))))))))))))))))))))))))))))))))))))))))))))", "))))))))))))))))))))))))))))))))))))))))))))))))))))))))))))))))", "))))))))))))))))))))))))))))))))))))))))))))))))))))))))))))))))", "))))))))))))))))))))))))))))))))))))))))))))))))))))))))))))))))", "))))))))))))))))))))))))))))))))))))))))))))))))))))))))))))))))", "))))))))))))))))))))))))))))))))))))))))))))))))))))))))))))))))", "))))))))))))))))))))))))))))))))))))))))))))))))))))))))))))))))", "))))))))))))))))))))))))))))))))))))))))))))))))))))))))))))))))", "))))))))))))))))))))))))))))))))))))))))))))))))))))))))))))))))", "))))))))))))))))))))))))))))))))))))))))))))))))))))))))))))))))", "))))))))))))))))))))))))))))))))))))))))))))))))))))))))))))))))", "))))))))))))))))))))))))))))))))))))))))))))))))))))))))))))))))", "))))))))))))))))))))))))))))))))))))))))))))))))))))))))))))))))", "))))))))))))))))))))))))))))))))))))))))))))))))))))))))))))))))", "))))))))))))))))))))))))))))))))))))))))))))))))))))))))))))))))", "))))))))))))))))))))))))))))))))))))))))))))))))))))))))))))))))", "))))))))))))))))))))))))))))))))))))))))))))))))))))))))))))))))", "))))))))))))))))))))))))))))))))))))))))))))))))))))))))))))))))", "))))))))))))))))))))))))))))))))))))))))))))))))))))))))))))))))", "))))))))))))))))))))))))))))))))))))))))))))))))))))))))))))))))"]}