{"keys": ["241506", "241507", "241508", "241509", "241510", "241511", "241512", "245829", "241496", "241497", "241498", "241499", "241500", "241501", "241502", "245819", "241148", "241149", "241150", "241151", "241152", "241153", "241154", "245109", "241138", "241139", "241140", "241141", "241142", "241143", "241144", "245099", "241128", "241129", "241130", "241131", "241132", "241133", "241134", "245089", "241118", "241119", "241120", "241121", "241122", "241123", "241124", "245079", "241108", "241109", "241110", "241111", "241112", "241113", "241114", "245069", "241098", "241099", "241100", "241101", "241102", "241103", "241104", "245059", "241088", "241089", "241090", "241091", "241092", "241093", "241094", "245049", "241078", "241079", "241080", "241081", "241082", "241083", "241084", "245039"], "data": {"241083": {"kc": 6, "oid_1": 241083, "rfor": 100, "run": 0, "rcoa": 0, "rorc": 0, "rtree": 0, "rara": 0, "valid": 1, "rabd": 0, "rwat": 0, "rtra": 0, "sc": 323, "rpad": 0, "cl6": 12, "rbuil": 0, "rsea": 0, "m3cd": 57393728, "cl3": 1}, "241082": {"kc": 6, "oid_1": 241082, "rfor": 100, "run": 0, "rcoa": 0, "rorc": 0, "rtree": 0, "rara": 0, "valid": 1, "rabd": 0, "rwat": 0, "rtra": 0, "sc": 324, "rpad": 0, "cl6": 12, "rbuil": 0, "rsea": 0, "m3cd": 57393727, "cl3": 1}, "241081": {"kc": 6, "oid_1": 241081, "rfor": 98.4, "run": 0, "rcoa": 0, "rorc": 0, "rtree": 0, "rara": 0, "valid": 1, "rabd": 1.6, "rwat": 0, "rtra": 0, "sc": 324, "rpad": 0, "cl6": 12, "rbuil": 0, "rsea": 0, "m3cd": 57393726, "cl3": 1}, "241080": {"kc": 6, "oid_1": 241080, "rfor": 77, "run": 0, "rcoa": 0, "rorc": 0, "rtree": 0, "rara": 0, "valid": 1, "rabd": 23, "rwat": 0, "rtra": 0, "sc": 322, "rpad": 0, "cl6": 12, "rbuil": 0, "rsea": 0, "m3cd": 57393725, "cl3": 1}, "241148": {"kc": 6, "oid_1": 241148, "rfor": 100, "run": 0, "rcoa": 0, "rorc": 0, "rtree": 0, "rara": 0, "valid": 1, "rabd": 0, "rwat": 0, "rtra": 0, "sc": 322, "rpad": 0, "cl6": 16, "rbuil": 0, "rsea": 0, "m3cd": 57393793, "cl3": 1}, "241084": {"kc": 6, "oid_1": 241084, "rfor": 100, "run": 0, "rcoa": 0, "rorc": 0, "rtree": 0, "rara": 0, "valid": 1, "rabd": 0, "rwat": 0, "rtra": 0, "sc": 323, "rpad": 0, "cl6": 16, "rbuil": 0, "rsea": 0, "m3cd": 57393729, "cl3": 1}, "241089": {"kc": 6, "oid_1": 241089, "rfor": 100, "run": 0, "rcoa": 0, "rorc": 0, "rtree": 0, "rara": 0, "valid": 1, "rabd": 0, "rwat": 0, "rtra": 0, "sc": 322, "rpad": 0, "cl6": 12, "rbuil": 0, "rsea": 0, "m3cd": 57393734, "cl3": 1}, "241088": {"kc": 6, "oid_1": 241088, "rfor": 98, "run": 0, "rcoa": 0, "rorc": 0, "rtree": 0, "rara": 0, "valid": 1, "rabd": 2, "rwat": 0, "rtra": 0, "sc": 322, "rpad": 0, "cl6": 12, "rbuil": 0, "rsea": 0, "m3cd": 57393733, "cl3": 1}, "241142": {"kc": 6, "oid_1": 241142, "rfor": 100, "run": 0, "rcoa": 0, "rorc": 0, "rtree": 0, "rara": 0, "valid": 1, "rabd": 0, "rwat": 0, "rtra": 0, "sc": 322, "rpad": 0, "cl6": 16, "rbuil": 0, "rsea": 0, "m3cd": 57393787, "cl3": 1}, "241143": {"kc": 6, "oid_1": 241143, "rfor": 100, "run": 0, "rcoa": 0, "rorc": 0, "rtree": 0, "rara": 0, "valid": 1, "rabd": 0, "rwat": 0, "rtra": 0, "sc": 322, "rpad": 0, "cl6": 16, "rbuil": 0, "rsea": 0, "m3cd": 57393788, "cl3": 1}, "241140": {"kc": 6, "oid_1": 241140, "rfor": 98.2, "run": 0, "rcoa": 0, "rorc": 0, "rtree": 0, "rara": 0, "valid": 1, "rabd": 1.8, "rwat": 0, "rtra": 0, "sc": 322, "rpad": 0, "cl6": 16, "rbuil": 0, "rsea": 0, "m3cd": 57393785, "cl3": 1}, "241141": {"kc": 6, "oid_1": 241141, "rfor": 100, "run": 0, "rcoa": 0, "rorc": 0, "rtree": 0, "rara": 0, "valid": 1, "rabd": 0, "rwat": 0, "rtra": 0, "sc": 322, "rpad": 0, "cl6": 16, "rbuil": 0, "rsea": 0, "m3cd": 57393786, "cl3": 1}, "241506": {"kc": 6, "oid_1": 241506, "rfor": 100, "run": 0, "rcoa": 0, "rorc": 0, "rtree": 0, "rara": 0, "valid": 1, "rabd": 0, "rwat": 0, "rtra": 0, "sc": 322, "rpad": 0, "cl6": 16, "rbuil": 0, "rsea": 0, "m3cd": 57394713, "cl3": 1}, "241507": {"kc": 6, "oid_1": 241507, "rfor": 100, "run": 0, "rcoa": 0, "rorc": 0, "rtree": 0, "rara": 0, "valid": 1, "rabd": 0, "rwat": 0, "rtra": 0, "sc": 322, "rpad": 0, "cl6": 16, "rbuil": 0, "rsea": 0, "m3cd": 57394714, "cl3": 1}, "241497": {"kc": 6, "oid_1": 241497, "rfor": 100, "run": 0, "rcoa": 0, "rorc": 0, "rtree": 0, "rara": 0, "valid": 1, "rabd": 0, "rwat": 0, "rtra": 0, "sc": 322, "rpad": 0, "cl6": 17, "rbuil": 0, "rsea": 0, "m3cd": 57394704, "cl3": 1}, "241502": {"kc": 6, "oid_1": 241502, "rfor": 97.6, "run": 0, "rcoa": 0, "rorc": 0, "rtree": 0, "rara": 0, "valid": 1, "rabd": 1.2, "rwat": 0, "rtra": 0, "sc": 322, "rpad": 1.1, "cl6": 17, "rbuil": 0, "rsea": 0, "m3cd": 57394709, "cl3": 1}, "241500": {"kc": 6, "oid_1": 241500, "rfor": 97.9, "run": 0, "rcoa": 0, "rorc": 0, "rtree": 0, "rara": 0, "valid": 1, "rabd": 2.1, "rwat": 0, "rtra": 0, "sc": 322, "rpad": 0, "cl6": 17, "rbuil": 0, "rsea": 0, "m3cd": 57394707, "cl3": 1}, "241501": {"kc": 6, "oid_1": 241501, "rfor": 98.8, "run": 0, "rcoa": 0, "rorc": 0, "rtree": 0, "rara": 0, "valid": 1, "rabd": 1.2, "rwat": 0, "rtra": 0, "sc": 322, "rpad": 0, "cl6": 16, "rbuil": 0, "rsea": 0, "m3cd": 57394708, "cl3": 1}, "245099": {"kc": 6, "oid_1": 245099, "rfor": 94.4, "run": 0, "rcoa": 0, "rorc": 0, "rtree": 0, "rara": 0, "valid": 1, "rabd": 3.5, "rwat": 0.6, "rtra": 0, "sc": 324, "rpad": 1.1, "cl6": 16, "rbuil": 0.4, "rsea": 0, "m3cd": 57403080, "cl3": 1}, "245109": {"kc": 6, "oid_1": 245109, "rfor": 100, "run": 0, "rcoa": 0, "rorc": 0, "rtree": 0, "rara": 0, "valid": 1, "rabd": 0, "rwat": 0, "rtra": 0, "sc": 324, "rpad": 0, "cl6": 16, "rbuil": 0, "rsea": 0, "m3cd": 57403090, "cl3": 1}, "241508": {"kc": 6, "oid_1": 241508, "rfor": 100, "run": 0, "rcoa": 0, "rorc": 0, "rtree": 0, "rara": 0, "valid": 1, "rabd": 0, "rwat": 0, "rtra": 0, "sc": 322, "rpad": 0, "cl6": 17, "rbuil": 0, "rsea": 0, "m3cd": 57394715, "cl3": 1}, "241509": {"kc": 6, "oid_1": 241509, "rfor": 100, "run": 0, "rcoa": 0, "rorc": 0, "rtree": 0, "rara": 0, "valid": 1, "rabd": 0, "rwat": 0, "rtra": 0, "sc": 322, "rpad": 0, "cl6": 17, "rbuil": 0, "rsea": 0, "m3cd": 57394716, "cl3": 1}, "241149": {"kc": 6, "oid_1": 241149, "rfor": 98.2, "run": 0, "rcoa": 0, "rorc": 0, "rtree": 0, "rara": 0, "valid": 1, "rabd": 1.8, "rwat": 0, "rtra": 0, "sc": 322, "rpad": 0, "cl6": 16, "rbuil": 0, "rsea": 0, "m3cd": 57393794, "cl3": 1}, "245069": {"kc": 6, "oid_1": 245069, "rfor": 99.9, "run": 0, "rcoa": 0, "rorc": 0, "rtree": 0, "rara": 0, "valid": 1, "rabd": 0, "rwat": 0.1, "rtra": 0, "sc": 323, "rpad": 0, "cl6": 16, "rbuil": 0, "rsea": 0, "m3cd": 57403050, "cl3": 1}, "241092": {"kc": 6, "oid_1": 241092, "rfor": 100, "run": 0, "rcoa": 0, "rorc": 0, "rtree": 0, "rara": 0, "valid": 1, "rabd": 0, "rwat": 0, "rtra": 0, "sc": 324, "rpad": 0, "cl6": 15, "rbuil": 0, "rsea": 0, "m3cd": 57393737, "cl3": 1}, "241512": {"kc": 6, "oid_1": 241512, "rfor": 97.6, "run": 0, "rcoa": 0, "rorc": 0, "rtree": 0, "rara": 0, "valid": 1, "rabd": 0.3, "rwat": 0, "rtra": 0, "sc": 322, "rpad": 2.1, "cl6": 17, "rbuil": 0, "rsea": 0, "m3cd": 57394719, "cl3": 1}, "241093": {"kc": 6, "oid_1": 241093, "rfor": 100, "run": 0, "rcoa": 0, "rorc": 0, "rtree": 0, "rara": 0, "valid": 1, "rabd": 0, "rwat": 0, "rtra": 0, "sc": 323, "rpad": 0, "cl6": 12, "rbuil": 0, "rsea": 0, "m3cd": 57393738, "cl3": 1}, "245829": {"kc": 6, "oid_1": 245829, "rfor": 100, "run": 0, "rcoa": 0, "rorc": 0, "rtree": 0, "rara": 0, "valid": 1, "rabd": 0, "rwat": 0, "rtra": 0, "sc": 322, "rpad": 0, "cl6": 17, "rbuil": 0, "rsea": 0, "m3cd": 57404010, "cl3": 1}, "241139": {"kc": 6, "oid_1": 241139, "rfor": 98.8, "run": 0, "rcoa": 0, "rorc": 0, "rtree": 0, "rara": 0, "valid": 1, "rabd": 0.8, "rwat": 0.4, "rtra": 0, "sc": 322, "rpad": 0, "cl6": 16, "rbuil": 0, "rsea": 0, "m3cd": 57393784, "cl3": 1}, "241111": {"kc": 6, "oid_1": 241111, "rfor": 100, "run": 0, "rcoa": 0, "rorc": 0, "rtree": 0, "rara": 0, "valid": 1, "rabd": 0, "rwat": 0, "rtra": 0, "sc": 324, "rpad": 0, "cl6": 15, "rbuil": 0, "rsea": 0, "m3cd": 57393756, "cl3": 1}, "241110": {"kc": 6, "oid_1": 241110, "rfor": 100, "run": 0, "rcoa": 0, "rorc": 0, "rtree": 0, "rara": 0, "valid": 1, "rabd": 0, "rwat": 0, "rtra": 0, "sc": 322, "rpad": 0, "cl6": 16, "rbuil": 0, "rsea": 0, "m3cd": 57393755, "cl3": 1}, "241113": {"kc": 6, "oid_1": 241113, "rfor": 100, "run": 0, "rcoa": 0, "rorc": 0, "rtree": 0, "rara": 0, "valid": 1, "rabd": 0, "rwat": 0, "rtra": 0, "sc": 324, "rpad": 0, "cl6": 16, "rbuil": 0, "rsea": 0, "m3cd": 57393758, "cl3": 1}, "241112": {"kc": 6, "oid_1": 241112, "rfor": 100, "run": 0, "rcoa": 0, "rorc": 0, "rtree": 0, "rara": 0, "valid": 1, "rabd": 0, "rwat": 0, "rtra": 0, "sc": 324, "rpad": 0, "cl6": 16, "rbuil": 0, "rsea": 0, "m3cd": 57393757, "cl3": 1}, "241114": {"kc": 6, "oid_1": 241114, "rfor": 100, "run": 0, "rcoa": 0, "rorc": 0, "rtree": 0, "rara": 0, "valid": 1, "rabd": 0, "rwat": 0, "rtra": 0, "sc": 324, "rpad": 0, "cl6": 16, "rbuil": 0, "rsea": 0, "m3cd": 57393759, "cl3": 1}, "241154": {"kc": 6, "oid_1": 241154, "rfor": 99.4, "run": 0, "rcoa": 0, "rorc": 0, "rtree": 0, "rara": 0, "valid": 1, "rabd": 0, "rwat": 0, "rtra": 0, "sc": 322, "rpad": 0.6, "cl6": 16, "rbuil": 0, "rsea": 0, "m3cd": 57393799, "cl3": 1}, "241119": {"kc": 6, "oid_1": 241119, "rfor": 100, "run": 0, "rcoa": 0, "rorc": 0, "rtree": 0, "rara": 0, "valid": 1, "rabd": 0, "rwat": 0, "rtra": 0, "sc": 322, "rpad": 0, "cl6": 12, "rbuil": 0, "rsea": 0, "m3cd": 57393764, "cl3": 1}, "241118": {"kc": 6, "oid_1": 241118, "rfor": 94.3, "run": 0, "rcoa": 0, "rorc": 0, "rtree": 0, "rara": 0, "valid": 1, "rabd": 5.7, "rwat": 0, "rtra": 0, "sc": 322, "rpad": 0, "cl6": 15, "rbuil": 0, "rsea": 0, "m3cd": 57393763, "cl3": 1}, "241131": {"kc": 6, "oid_1": 241131, "rfor": 100, "run": 0, "rcoa": 0, "rorc": 0, "rtree": 0, "rara": 0, "valid": 1, "rabd": 0, "rwat": 0, "rtra": 0, "sc": 322, "rpad": 0, "cl6": 16, "rbuil": 0, "rsea": 0, "m3cd": 57393776, "cl3": 1}, "241130": {"kc": 6, "oid_1": 241130, "rfor": 97.2, "run": 0, "rcoa": 0, "rorc": 0, "rtree": 0, "rara": 0, "valid": 1, "rabd": 2.8, "rwat": 0, "rtra": 0, "sc": 322, "rpad": 0, "cl6": 16, "rbuil": 0, "rsea": 0, "m3cd": 57393775, "cl3": 1}, "241144": {"kc": 6, "oid_1": 241144, "rfor": 100, "run": 0, "rcoa": 0, "rorc": 0, "rtree": 0, "rara": 0, "valid": 1, "rabd": 0, "rwat": 0, "rtra": 0, "sc": 324, "rpad": 0, "cl6": 16, "rbuil": 0, "rsea": 0, "m3cd": 57393789, "cl3": 1}, "241134": {"kc": 6, "oid_1": 241134, "rfor": 98.9, "run": 0, "rcoa": 0, "rorc": 0, "rtree": 0, "rara": 0, "valid": 1, "rabd": 0, "rwat": 0, "rtra": 0, "sc": 324, "rpad": 1.1, "cl6": 16, "rbuil": 0, "rsea": 0, "m3cd": 57393779, "cl3": 1}, "241094": {"kc": 6, "oid_1": 241094, "rfor": 100, "run": 0, "rcoa": 0, "rorc": 0, "rtree": 0, "rara": 0, "valid": 1, "rabd": 0, "rwat": 0, "rtra": 0, "sc": 323, "rpad": 0, "cl6": 16, "rbuil": 0, "rsea": 0, "m3cd": 57393739, "cl3": 1}, "241499": {"kc": 6, "oid_1": 241499, "rfor": 100, "run": 0, "rcoa": 0, "rorc": 0, "rtree": 0, "rara": 0, "valid": 1, "rabd": 0, "rwat": 0, "rtra": 0, "sc": 322, "rpad": 0, "cl6": 17, "rbuil": 0, "rsea": 0, "m3cd": 57394706, "cl3": 1}, "241090": {"kc": 6, "oid_1": 241090, "rfor": 100, "run": 0, "rcoa": 0, "rorc": 0, "rtree": 0, "rara": 0, "valid": 1, "rabd": 0, "rwat": 0, "rtra": 0, "sc": 322, "rpad": 0, "cl6": 12, "rbuil": 0, "rsea": 0, "m3cd": 57393735, "cl3": 1}, "241091": {"kc": 6, "oid_1": 241091, "rfor": 100, "run": 0, "rcoa": 0, "rorc": 0, "rtree": 0, "rara": 0, "valid": 1, "rabd": 0, "rwat": 0, "rtra": 0, "sc": 324, "rpad": 0, "cl6": 15, "rbuil": 0, "rsea": 0, "m3cd": 57393736, "cl3": 1}, "241078": {"kc": 6, "oid_1": 241078, "rfor": 48.7, "run": 0, "rcoa": 0, "rorc": 0, "rtree": 0, "rara": 0, "valid": 1, "rabd": 51.3, "rwat": 0, "rtra": 0, "sc": 322, "rpad": 0, "cl6": 12, "rbuil": 0, "rsea": 0, "m3cd": 57393723, "cl3": 1}, "241079": {"kc": 6, "oid_1": 241079, "rfor": 78.4, "run": 0, "rcoa": 0, "rorc": 0, "rtree": 0, "rara": 0, "valid": 1, "rabd": 21.6, "rwat": 0, "rtra": 0, "sc": 322, "rpad": 0, "cl6": 12, "rbuil": 0, "rsea": 0, "m3cd": 57393724, "cl3": 1}, "241151": {"kc": 6, "oid_1": 241151, "rfor": 97.6, "run": 0, "rcoa": 0, "rorc": 0, "rtree": 0, "rara": 0, "valid": 1, "rabd": 2.4, "rwat": 0, "rtra": 0, "sc": 322, "rpad": 0, "cl6": 17, "rbuil": 0, "rsea": 0, "m3cd": 57393796, "cl3": 1}, "241138": {"kc": 6, "oid_1": 241138, "rfor": 94.7, "run": 0, "rcoa": 0, "rorc": 0, "rtree": 0, "rara": 0, "valid": 1, "rabd": 0, "rwat": 5.3, "rtra": 0, "sc": 322, "rpad": 0, "cl6": 16, "rbuil": 0, "rsea": 0, "m3cd": 57393783, "cl3": 1}, "245079": {"kc": 6, "oid_1": 245079, "rfor": 99.6, "run": 0, "rcoa": 0, "rorc": 0, "rtree": 0, "rara": 0, "valid": 1, "rabd": 0.3, "rwat": 0, "rtra": 0, "sc": 324, "rpad": 0, "cl6": 16, "rbuil": 0, "rsea": 0, "m3cd": 57403060, "cl3": 1}, "241098": {"kc": 6, "oid_1": 241098, "rfor": 100, "run": 0, "rcoa": 0, "rorc": 0, "rtree": 0, "rara": 0, "valid": 1, "rabd": 0, "rwat": 0, "rtra": 0, "sc": 322, "rpad": 0, "cl6": 12, "rbuil": 0, "rsea": 0, "m3cd": 57393743, "cl3": 1}, "241099": {"kc": 6, "oid_1": 241099, "rfor": 100, "run": 0, "rcoa": 0, "rorc": 0, "rtree": 0, "rara": 0, "valid": 1, "rabd": 0, "rwat": 0, "rtra": 0, "sc": 322, "rpad": 0, "cl6": 16, "rbuil": 0, "rsea": 0, "m3cd": 57393744, "cl3": 1}, "241153": {"kc": 6, "oid_1": 241153, "rfor": 100, "run": 0, "rcoa": 0, "rorc": 0, "rtree": 0, "rara": 0, "valid": 1, "rabd": 0, "rwat": 0, "rtra": 0, "sc": 322, "rpad": 0, "cl6": 16, "rbuil": 0, "rsea": 0, "m3cd": 57393798, "cl3": 1}, "241150": {"kc": 6, "oid_1": 241150, "rfor": 100, "run": 0, "rcoa": 0, "rorc": 0, "rtree": 0, "rara": 0, "valid": 1, "rabd": 0, "rwat": 0, "rtra": 0, "sc": 322, "rpad": 0, "cl6": 17, "rbuil": 0, "rsea": 0, "m3cd": 57393795, "cl3": 1}, "241498": {"kc": 6, "oid_1": 241498, "rfor": 100, "run": 0, "rcoa": 0, "rorc": 0, "rtree": 0, "rara": 0, "valid": 1, "rabd": 0, "rwat": 0, "rtra": 0, "sc": 322, "rpad": 0, "cl6": 17, "rbuil": 0, "rsea": 0, "m3cd": 57394705, "cl3": 1}, "241133": {"kc": 6, "oid_1": 241133, "rfor": 100, "run": 0, "rcoa": 0, "rorc": 0, "rtree": 0, "rara": 0, "valid": 1, "rabd": 0, "rwat": 0, "rtra": 0, "sc": 324, "rpad": 0, "cl6": 16, "rbuil": 0, "rsea": 0, "m3cd": 57393778, "cl3": 1}, "241511": {"kc": 6, "oid_1": 241511, "rfor": 98.9, "run": 0, "rcoa": 0, "rorc": 0, "rtree": 0, "rara": 0, "valid": 1, "rabd": 0.6, "rwat": 0, "rtra": 0, "sc": 322, "rpad": 0.5, "cl6": 17, "rbuil": 0, "rsea": 0, "m3cd": 57394718, "cl3": 1}, "241496": {"kc": 6, "oid_1": 241496, "rfor": 100, "run": 0, "rcoa": 0, "rorc": 0, "rtree": 0, "rara": 0, "valid": 1, "rabd": 0, "rwat": 0, "rtra": 0, "sc": 322, "rpad": 0, "cl6": 16, "rbuil": 0, "rsea": 0, "m3cd": 57394703, "cl3": 1}, "245089": {"kc": 6, "oid_1": 245089, "rfor": 96.6, "run": 0, "rcoa": 0, "rorc": 0, "rtree": 0, "rara": 0, "valid": 1, "rabd": 3, "rwat": 0, "rtra": 0, "sc": 324, "rpad": 0.2, "cl6": 16, "rbuil": 0.2, "rsea": 0, "m3cd": 57403070, "cl3": 1}, "241132": {"kc": 6, "oid_1": 241132, "rfor": 100, "run": 0, "rcoa": 0, "rorc": 0, "rtree": 0, "rara": 0, "valid": 1, "rabd": 0, "rwat": 0, "rtra": 0, "sc": 322, "rpad": 0, "cl6": 16, "rbuil": 0, "rsea": 0, "m3cd": 57393777, "cl3": 1}, "241152": {"kc": 6, "oid_1": 241152, "rfor": 99.9, "run": 0, "rcoa": 0, "rorc": 0, "rtree": 0, "rara": 0, "valid": 1, "rabd": 0.1, "rwat": 0, "rtra": 0, "sc": 322, "rpad": 0, "cl6": 17, "rbuil": 0, "rsea": 0, "m3cd": 57393797, "cl3": 1}, "245059": {"kc": 6, "oid_1": 245059, "rfor": 99.6, "run": 0, "rcoa": 0, "rorc": 0, "rtree": 0, "rara": 0, "valid": 1, "rabd": 0, "rwat": 0.4, "rtra": 0, "sc": 323, "rpad": 0, "cl6": 16, "rbuil": 0, "rsea": 0, "m3cd": 57403040, "cl3": 1}, "245039": {"kc": 6, "oid_1": 245039, "rfor": 100, "run": 0, "rcoa": 0, "rorc": 0, "rtree": 0, "rara": 0, "valid": 1, "rabd": 0, "rwat": 0, "rtra": 0, "sc": 323, "rpad": 0, "cl6": 16, "rbuil": 0, "rsea": 0, "m3cd": 57403020, "cl3": 1}, "245819": {"kc": 6, "oid_1": 245819, "rfor": 92.1, "run": 0, "rcoa": 0, "rorc": 0, "rtree": 0, "rara": 0, "valid": 1, "rabd": 7.9, "rwat": 0, "rtra": 0, "sc": 322, "rpad": 0, "cl6": 17, "rbuil": 0, "rsea": 0, "m3cd": 57404000, "cl3": 1}, "241510": {"kc": 6, "oid_1": 241510, "rfor": 92.1, "run": 0, "rcoa": 0, "rorc": 0, "rtree": 0, "rara": 0, "valid": 1, "rabd": 5.4, "rwat": 2.5, "rtra": 0, "sc": 322, "rpad": 0, "cl6": 17, "rbuil": 0, "rsea": 0, "m3cd": 57394717, "cl3": 1}, "241102": {"kc": 6, "oid_1": 241102, "rfor": 95.8, "run": 0, "rcoa": 0, "rorc": 0, "rtree": 0, "rara": 0, "valid": 1, "rabd": 4.2, "rwat": 0, "rtra": 0, "sc": 324, "rpad": 0, "cl6": 16, "rbuil": 0, "rsea": 0, "m3cd": 57393747, "cl3": 1}, "241103": {"kc": 6, "oid_1": 241103, "rfor": 100, "run": 0, "rcoa": 0, "rorc": 0, "rtree": 0, "rara": 0, "valid": 1, "rabd": 0, "rwat": 0, "rtra": 0, "sc": 324, "rpad": 0, "cl6": 15, "rbuil": 0, "rsea": 0, "m3cd": 57393748, "cl3": 1}, "241100": {"kc": 6, "oid_1": 241100, "rfor": 100, "run": 0, "rcoa": 0, "rorc": 0, "rtree": 0, "rara": 0, "valid": 1, "rabd": 0, "rwat": 0, "rtra": 0, "sc": 322, "rpad": 0, "cl6": 12, "rbuil": 0, "rsea": 0, "m3cd": 57393745, "cl3": 1}, "241101": {"kc": 6, "oid_1": 241101, "rfor": 100, "run": 0, "rcoa": 0, "rorc": 0, "rtree": 0, "rara": 0, "valid": 1, "rabd": 0, "rwat": 0, "rtra": 0, "sc": 324, "rpad": 0, "cl6": 15, "rbuil": 0, "rsea": 0, "m3cd": 57393746, "cl3": 1}, "241128": {"kc": 6, "oid_1": 241128, "rfor": 100, "run": 0, "rcoa": 0, "rorc": 0, "rtree": 0, "rara": 0, "valid": 1, "rabd": 0, "rwat": 0, "rtra": 0, "sc": 322, "rpad": 0, "cl6": 16, "rbuil": 0, "rsea": 0, "m3cd": 57393773, "cl3": 1}, "241129": {"kc": 6, "oid_1": 241129, "rfor": 100, "run": 0, "rcoa": 0, "rorc": 0, "rtree": 0, "rara": 0, "valid": 1, "rabd": 0, "rwat": 0, "rtra": 0, "sc": 322, "rpad": 0, "cl6": 16, "rbuil": 0, "rsea": 0, "m3cd": 57393774, "cl3": 1}, "241104": {"kc": 6, "oid_1": 241104, "rfor": 100, "run": 0, "rcoa": 0, "rorc": 0, "rtree": 0, "rara": 0, "valid": 1, "rabd": 0, "rwat": 0, "rtra": 0, "sc": 323, "rpad": 0, "cl6": 16, "rbuil": 0, "rsea": 0, "m3cd": 57393749, "cl3": 1}, "241124": {"kc": 6, "oid_1": 241124, "rfor": 100, "run": 0, "rcoa": 0, "rorc": 0, "rtree": 0, "rara": 0, "valid": 1, "rabd": 0, "rwat": 0, "rtra": 0, "sc": 324, "rpad": 0, "cl6": 16, "rbuil": 0, "rsea": 0, "m3cd": 57393769, "cl3": 1}, "245049": {"kc": 6, "oid_1": 245049, "rfor": 99.1, "run": 0, "rcoa": 0, "rorc": 0, "rtree": 0, "rara": 0, "valid": 1, "rabd": 0, "rwat": 0.9, "rtra": 0, "sc": 323, "rpad": 0, "cl6": 16, "rbuil": 0, "rsea": 0, "m3cd": 57403030, "cl3": 1}, "241108": {"kc": 6, "oid_1": 241108, "rfor": 86, "run": 0, "rcoa": 0, "rorc": 0, "rtree": 0, "rara": 0, "valid": 1, "rabd": 14, "rwat": 0, "rtra": 0, "sc": 322, "rpad": 0, "cl6": 15, "rbuil": 0, "rsea": 0, "m3cd": 57393753, "cl3": 1}, "241109": {"kc": 6, "oid_1": 241109, "rfor": 98.6, "run": 0, "rcoa": 0, "rorc": 0, "rtree": 0, "rara": 0, "valid": 1, "rabd": 1.4, "rwat": 0, "rtra": 0, "sc": 322, "rpad": 0, "cl6": 16, "rbuil": 0, "rsea": 0, "m3cd": 57393754, "cl3": 1}, "241120": {"kc": 6, "oid_1": 241120, "rfor": 98.4, "run": 0, "rcoa": 0, "rorc": 0, "rtree": 0, "rara": 0, "valid": 1, "rabd": 1.6, "rwat": 0, "rtra": 0, "sc": 322, "rpad": 0, "cl6": 16, "rbuil": 0, "rsea": 0, "m3cd": 57393765, "cl3": 1}, "241121": {"kc": 6, "oid_1": 241121, "rfor": 100, "run": 0, "rcoa": 0, "rorc": 0, "rtree": 0, "rara": 0, "valid": 1, "rabd": 0, "rwat": 0, "rtra": 0, "sc": 322, "rpad": 0, "cl6": 16, "rbuil": 0, "rsea": 0, "m3cd": 57393766, "cl3": 1}, "241122": {"kc": 6, "oid_1": 241122, "rfor": 100, "run": 0, "rcoa": 0, "rorc": 0, "rtree": 0, "rara": 0, "valid": 1, "rabd": 0, "rwat": 0, "rtra": 0, "sc": 324, "rpad": 0, "cl6": 16, "rbuil": 0, "rsea": 0, "m3cd": 57393767, "cl3": 1}, "241123": {"kc": 6, "oid_1": 241123, "rfor": 100, "run": 0, "rcoa": 0, "rorc": 0, "rtree": 0, "rara": 0, "valid": 1, "rabd": 0, "rwat": 0, "rtra": 0, "sc": 324, "rpad": 0, "cl6": 16, "rbuil": 0, "rsea": 0, "m3cd": 57393768, "cl3": 1}}, "grid": ["  !!!!!!!!!!#########$$$$$$$$$%%%%%%%%%&&&&&&&&&'''''''''(((((((", "))**********+++++++++,,,,,,,,,---------........./////////0000000", "))**********+++++++++,,,,,,,,,---------........./////////0000000", "))**********+++++++++,,,,,,,,,---------........./////////0000000", "))**********+++++++++,,,,,,,,,---------........./////////0000000", "))**********+++++++++,,,,,,,,,---------........./////////0000000", "))**********+++++++++,,,,,,,,,---------........./////////0000000", "))**********+++++++++,,,,,,,,,---------........./////////0000000", "1122222222223333333334444444445555555556666666667777777778888888", "1122222222223333333334444444445555555556666666667777777778888888", "1122222222223333333334444444445555555556666666667777777778888888", "1122222222223333333334444444445555555556666666667777777778888888", "1122222222223333333334444444445555555556666666667777777778888888", "1122222222223333333334444444445555555556666666667777777778888888", "1122222222223333333334444444445555555556666666667777777778888888", "1122222222223333333334444444445555555556666666667777777778888888", "99::::::::::;;;;;;;;;<<<<<<<<<=========>>>>>>>>>?????????@@@@@@@", "99::::::::::;;;;;;;;;<<<<<<<<<=========>>>>>>>>>?????????@@@@@@@", "99::::::::::;;;;;;;;;<<<<<<<<<=========>>>>>>>>>?????????@@@@@@@", "99::::::::::;;;;;;;;;<<<<<<<<<=========>>>>>>>>>?????????@@@@@@@", "99::::::::::;;;;;;;;;<<<<<<<<<=========>>>>>>>>>?????????@@@@@@@", "99::::::::::;;;;;;;;;<<<<<<<<<=========>>>>>>>>>?????????@@@@@@@", "99::::::::::;;;;;;;;;<<<<<<<<<=========>>>>>>>>>?????????@@@@@@@", "99::::::::::;;;;;;;;;<<<<<<<<<=========>>>>>>>>>?????????@@@@@@@", "AABBBBBBBBBBCCCCCCCCCDDDDDDDDDEEEEEEEEEFFFFFFFFFGGGGGGGGGHHHHHHH", "AABBBBBBBBBBCCCCCCCCCDDDDDDDDDEEEEEEEEEFFFFFFFFFGGGGGGGGGHHHHHHH", "AABBBBBBBBBBCCCCCCCCCDDDDDDDDDEEEEEEEEEFFFFFFFFFGGGGGGGGGHHHHHHH", "AABBBBBBBBBBCCCCCCCCCDDDDDDDDDEEEEEEEEEFFFFFFFFFGGGGGGGGGHHHHHHH", "AABBBBBBBBBBCCCCCCCCCDDDDDDDDDEEEEEEEEEFFFFFFFFFGGGGGGGGGHHHHHHH", "AABBBBBBBBBBCCCCCCCCCDDDDDDDDDEEEEEEEEEFFFFFFFFFGGGGGGGGGHHHHHHH", "AABBBBBBBBBBCCCCCCCCCDDDDDDDDDEEEEEEEEEFFFFFFFFFGGGGGGGGGHHHHHHH", "IIJJJJJJJJJJKKKKKKKKKLLLLLLLLLMMMMMMMMMNNNNNNNNNOOOOOOOOOPPPPPPP", "IIJJJJJJJJJJKKKKKKKKKLLLLLLLLLMMMMMMMMMNNNNNNNNNOOOOOOOOOPPPPPPP", "IIJJJJJJJJJJKKKKKKKKKLLLLLLLLLMMMMMMMMMNNNNNNNNNOOOOOOOOOPPPPPPP", "IIJJJJJJJJJJKKKKKKKKKLLLLLLLLLMMMMMMMMMNNNNNNNNNOOOOOOOOOPPPPPPP", "IIJJJJJJJJJJKKKKKKKKKLLLLLLLLLMMMMMMMMMNNNNNNNNNOOOOOOOOOPPPPPPP", "IIJJJJJJJJJJKKKKKKKKKLLLLLLLLLMMMMMMMMMNNNNNNNNNOOOOOOOOOPPPPPPP", "IIJJJJJJJJJJKKKKKKKKKLLLLLLLLLMMMMMMMMMNNNNNNNNNOOOOOOOOOPPPPPPP", "IIJJJJJJJJJJKKKKKKKKKLLLLLLLLLMMMMMMMMMNNNNNNNNNOOOOOOOOOPPPPPPP", "QQRRRRRRRRRRSSSSSSSSSTTTTTTTTTUUUUUUUUUVVVVVVVVVWWWWWWWWWXXXXXXX", "QQRRRRRRRRRRSSSSSSSSSTTTTTTTTTUUUUUUUUUVVVVVVVVVWWWWWWWWWXXXXXXX", "QQRRRRRRRRRRSSSSSSSSSTTTTTTTTTUUUUUUUUUVVVVVVVVVWWWWWWWWWXXXXXXX", "QQRRRRRRRRRRSSSSSSSSSTTTTTTTTTUUUUUUUUUVVVVVVVVVWWWWWWWWWXXXXXXX", "QQRRRRRRRRRRSSSSSSSSSTTTTTTTTTUUUUUUUUUVVVVVVVVVWWWWWWWWWXXXXXXX", "QQRRRRRRRRRRSSSSSSSSSTTTTTTTTTUUUUUUUUUVVVVVVVVVWWWWWWWWWXXXXXXX", "QQRRRRRRRRRRSSSSSSSSSTTTTTTTTTUUUUUUUUUVVVVVVVVVWWWWWWWWWXXXXXXX", "QQRRRRRRRRRRSSSSSSSSSTTTTTTTTTUUUUUUUUUVVVVVVVVVWWWWWWWWWXXXXXXX", "YYZZZZZZZZZZ[[[[[[[[[]]]]]]]]]^^^^^^^^^_________`````````aaaaaaa", "YYZZZZZZZZZZ[[[[[[[[[]]]]]]]]]^^^^^^^^^_________`````````aaaaaaa", "YYZZZZZZZZZZ[[[[[[[[[]]]]]]]]]^^^^^^^^^_________`````````aaaaaaa", "YYZZZZZZZZZZ[[[[[[[[[]]]]]]]]]^^^^^^^^^_________`````````aaaaaaa", "YYZZZZZZZZZZ[[[[[[[[[]]]]]]]]]^^^^^^^^^_________`````````aaaaaaa", "YYZZZZZZZZZZ[[[[[[[[[]]]]]]]]]^^^^^^^^^_________`````````aaaaaaa", "YYZZZZZZZZZZ[[[[[[[[[]]]]]]]]]^^^^^^^^^_________`````````aaaaaaa", "YYZZZZZZZZZZ[[[[[[[[[]]]]]]]]]^^^^^^^^^_________`````````aaaaaaa", "bbccccccccccdddddddddeeeeeeeeefffffffffggggggggghhhhhhhhhiiiiiii", "bbccccccccccdddddddddeeeeeeeeefffffffffggggggggghhhhhhhhhiiiiiii", "bbccccccccccdddddddddeeeeeeeeefffffffffggggggggghhhhhhhhhiiiiiii", "bbccccccccccdddddddddeeeeeeeeefffffffffggggggggghhhhhhhhhiiiiiii", "bbccccccccccdddddddddeeeeeeeeefffffffffggggggggghhhhhhhhhiiiiiii", "bbccccccccccdddddddddeeeeeeeeefffffffffggggggggghhhhhhhhhiiiiiii", "bbccccccccccdddddddddeeeeeeeeefffffffffggggggggghhhhhhhhhiiiiiii", "jjkkkkkkkkkklllllllllmmmmmmmmmnnnnnnnnnooooooooopppppppppqqqqqqq", "jjkkkkkkkkkklllllllllmmmmmmmmmnnnnnnnnnooooooooopppppppppqqqqqqq"]}